oy3o/_.py
oy3o/__init__.py
oy3o/input.py
oy3o/list.py
oy3o/string.py
oy3o/terminal.py
oy3o/editor/__init__.py
oy3o/editor/__main__.py
oy3o/editor/editor.py
oy3o/flow/__init__.py
oy3o/flow/__main__.py
oy3o/flow/flow.py
oy3o-0.2.0.dist-info/licenses/LICENSE
oy3o-0.2.0.dist-info/METADATA
oy3o-0.2.0.dist-info/WHEEL
oy3o-0.2.0.dist-info/top_level.txt
oy3o-0.2.0.dist-info/RECORD
