Metadata-Version: 2.4
Name: oy3o
Version: 0.2.0
Summary: oy3o 命名空间，包含一些子包
Author-email: oy3o <python@oy3o.com>
License: MIT License
Project-URL: Homepage, https://github.com/oy3o/python
Project-URL: Repository, https://github.com/oy3o/python
Keywords: tui,editor,curses,oy3o
Classifier: Development Status :: 3 - Alpha
Classifier: Intended Audience :: Developers
Classifier: License :: OSI Approved :: MIT License
Classifier: Programming Language :: Python :: 3
Classifier: Programming Language :: Python :: 3.8
Classifier: Programming Language :: Python :: 3.9
Classifier: Programming Language :: Python :: 3.10
Classifier: Programming Language :: Python :: 3.11
Classifier: Programming Language :: Python :: 3.12
Classifier: Topic :: Software Development :: Libraries :: Python Modules
Classifier: Topic :: Terminals
Classifier: Environment :: Console :: Curses
Requires-Python: >=3.8
License-File: LICENSE
Requires-Dist: pyperclip
Requires-Dist: wcwidth
Requires-Dist: tiktoken
Requires-Dist: numba
Requires-Dist: deco
Requires-Dist: typing-extensions
Dynamic: license-file
